pydantic_xlsx/__init__.py
pydantic_xlsx/composition.py
pydantic_xlsx/config.py
pydantic_xlsx/conversion.py
pydantic_xlsx/fields.py
pydantic_xlsx/model.py
pydantic_xlsx/money.py
pydantic_xlsx/types.py
pydantic_xlsx-0.1.0.dist-info/METADATA
pydantic_xlsx-0.1.0.dist-info/WHEEL
pydantic_xlsx-0.1.0.dist-info/licenses/LICENSE
pydantic_xlsx-0.1.0.dist-info/RECORD
