Metadata-Version: 2.4
Name: pydantic-xlsx
Version: 0.1.0
Summary: Parsing and dumping from and to Excel's xlsx files using pydantic Models.
License-File: LICENSE
Requires-Python: >=3.12
Requires-Dist: openpyxl>=3.1.5
Requires-Dist: pydantic>=2.10.6
